[
	{
		"config": {
			"title": "home",
			"type": "page"
		},
		"contents": [
			{
				"config": {
					"type": "row",
					"class": {
						"outer": "",
						"inner": "white-txt center pad-200-20-120"
					},
					"bg": {
						"img": "http://i.imgur.com/gjxFlQ1.gif",
						"color": "#075",
						"size": "cover",
						"repeat": "no-repeat",
						"position": "",
						"attachment": "fixed",
						"opacity": 0.5,
						"parallax": 0.2
					}
				},
				"contents": [
					{
						"config": {
							"type": "image",
							"class": "center",
							"size": "",
							"src": "client/images/nsc-logo.png",
							"alt": "North State Consulting logo"
						},
						"contents": null
					},
					{
						"config": {
							"type": "h1",
							"text": "North State Consulting"
						},
						"contents": null
					},
					{
						"config": {
							"type": "p",
							"text": "Custom web hosting solutions and consulting services for businesses of all sizes"
						},
						"contents": null
					},
					{
						"config": {
							"type": "block",
							"class": "pad",
							"size": "full"
						},
						"contents": [
							{
								"config": {
									"type": "button",
									"id": "",
									"class": "center pad",
									"size": "",
									"name": "",
									"buttontype": "",
									"value": "",
									"form": "",
									"click": "",
									"text": "Get started",
									"link": "#",
									"target": ""
								},
								"contents": null
							}
						]
					}
				]
			},
			{
				"config": {
					"type": "row",
					"class": {
						"outer": "",
						"inner": "pad-20-0 center"
					},
					"bg": {
						"img": "",
						"color": "#fff",
						"size": "",
						"repeat": "",
						"position": "",
						"attachment": "",
						"opacity": 0,
						"parallax": null
					}
				},
				"contents": [
					{
						"config": {
							"type": "block",
							"class": "pad-20",
							"size": "third"
						},
						"contents": [
							{
								"config": {
									"type": "image",
									"class": "circle border-2px-444",
									"size": "",
									"src": "client/images/nsc-icon-hosting.png",
									"alt": "Hosting"
								},
								"contents": null
							},
							{
								"config": {
									"type": "h3",
									"text": "Hosting"
								},
								"contents": null
							},
							{
								"config": {
									"type": "p",
									"text": "Lorem ipsum dolor sit amet, aenean elit magna cursus pulvinar vel sollicitudin, et tortor in, dolor dapibus fringilla."
								},
								"contents": null
							}
						]
					},
					{
						"config": {
							"type": "block",
							"class": "pad-20",
							"size": "third"
						},
						"contents": [
							{
								"config": {
									"type": "image",
									"class": "circle border-2px-444",
									"size": "",
									"src": "client/images/nsc-icon-security.png",
									"alt": "Security"
								},
								"contents": null
							},
							{
								"config": {
									"type": "h3",
									"text": "Security"
								},
								"contents": null
							},
							{
								"config": {
									"type": "p",
									"text": "Lorem ipsum dolor sit amet, aenean elit magna cursus pulvinar vel sollicitudin, et tortor in, dolor dapibus fringilla."
								},
								"contents": null
							}
						]
					},
					{
						"config": {
							"type": "block",
							"class": "pad-20",
							"size": "third"
						},
						"contents": [
							{
								"config": {
									"type": "image",
									"class": "circle border-2px-444",
									"size": "",
									"src": "client/images/nsc-icon-support.png",
									"alt": "Support"
								},
								"contents": null
							},
							{
								"config": {
									"type": "h3",
									"text": "Support"
								},
								"contents": null
							},
							{
								"config": {
									"type": "p",
									"text": "Lorem ipsum dolor sit amet, aenean elit magna cursus pulvinar vel sollicitudin, et tortor in, dolor dapibus fringilla."
								},
								"contents": null
							}
						]
					}
				]
			},
			{
				"config": {
					"type": "row",
					"class": {
						"outer": "",
						"inner": "pad-20-0"
					},
					"bg": {
						"img": "",
						"color": "#f3f3f3",
						"size": "",
						"repeat": "",
						"position": "",
						"attachment": "",
						"opacity": 0,
						"parallax": null
					}
				},
				"contents": [
					{
						"config": {
							"type": "block",
							"class": "pad-20",
							"size": "half"
						},
						"contents": [
							{
								"config": {
									"type": "h3",
									"text": "Launch your website today!"
								},
								"contents": null
							},
							{
								"config": {
									"type": "p",
									"text": "Lorem ipsum dolor sit amet, aenean elit magna cursus pulvinar vel sollicitudin, et tortor in, dolor dapibus fringilla."
								},
								"contents": null
							}
						]
					},
					{
						"config": {
							"type": "block",
							"class": "pad-20",
							"size": "half"
						},
						"contents": [
							{
								"config": {
									"type": "block",
									"class": "pad-20 primary-bg white-txt",
									"size": "full"
								},
								"contents": [
									{
										"config": {
											"type": "h3",
											"text": "Contact Form"
										},
										"contents": null
									}
								]
							}
						]
					}
				]
			}
		]
	}
]